MPP/MPP.py
MPP/__init__.py
MPP/core.py
MPP/kernel.py
MPP/plot.py
MPP/random_to_png.py
MPP/run.py
MPP/sankey_gap.py
MPP/utils.py
MPP/graph/__init__.py
MPP/graph/curved_edges.py
MPP/graph/kinetic_network.py
mpp_lumping-0.9.1.dist-info/METADATA
mpp_lumping-0.9.1.dist-info/WHEEL
mpp_lumping-0.9.1.dist-info/licenses/LICENSE
mpp_lumping-0.9.1.dist-info/RECORD
