Metadata-Version: 2.4
Name: mpp-lumping
Version: 0.9.1
Summary: Lumping tool for state trajectories
Project-URL: Homepage, https://github.com/moldyn/MPP
Project-URL: Issues, https://github.com/moldyn/MPP/issues
Author-email: Felix Guischard <felix0180@web.de>
License: MIT License
License-File: LICENSE
Classifier: License :: OSI Approved :: MIT License
Classifier: Operating System :: OS Independent
Classifier: Programming Language :: Python :: 3
Requires-Python: >=3.10
Requires-Dist: anytree>=2.12.1
Requires-Dist: bezier>=2024.6.20
Requires-Dist: fa2-modified>=0.3.10
Requires-Dist: mdtraj>=1.11.0
Requires-Dist: msmhelper>=1.1.1
Requires-Dist: networkx>=3.5
Requires-Dist: numpy>=2.2.5
Requires-Dist: pygpcca>=1.0.4
Requires-Dist: pyyaml>=6.0.2
Requires-Dist: scikit-learn>=1.7.2
Requires-Dist: seaborn>=0.13.2
Requires-Dist: tqdm>=4.67.1
